MANIFEST.in
README.rst
setup.py
aliyun_python_sdk_chatbot.egg-info/PKG-INFO
aliyun_python_sdk_chatbot.egg-info/SOURCES.txt
aliyun_python_sdk_chatbot.egg-info/dependency_links.txt
aliyun_python_sdk_chatbot.egg-info/requires.txt
aliyun_python_sdk_chatbot.egg-info/top_level.txt
aliyunsdkchatbot/__init__.py
aliyunsdkchatbot/request/__init__.py
aliyunsdkchatbot/request/v20171011/ActivatePerspectiveRequest.py
aliyunsdkchatbot/request/v20171011/AddSynonymRequest.py
aliyunsdkchatbot/request/v20171011/AppendEntityMemberRequest.py
aliyunsdkchatbot/request/v20171011/ChatRequest.py
aliyunsdkchatbot/request/v20171011/CreateCategoryRequest.py
aliyunsdkchatbot/request/v20171011/CreateCoreWordRequest.py
aliyunsdkchatbot/request/v20171011/CreateDialogRequest.py
aliyunsdkchatbot/request/v20171011/CreateEntityRequest.py
aliyunsdkchatbot/request/v20171011/CreateIntentRequest.py
aliyunsdkchatbot/request/v20171011/CreateKnowledgeRequest.py
aliyunsdkchatbot/request/v20171011/CreatePerspectiveRequest.py
aliyunsdkchatbot/request/v20171011/DeleteCategoryRequest.py
aliyunsdkchatbot/request/v20171011/DeleteDialogRequest.py
aliyunsdkchatbot/request/v20171011/DeleteEntityRequest.py
aliyunsdkchatbot/request/v20171011/DeleteIntentRequest.py
aliyunsdkchatbot/request/v20171011/DeleteKnowledgeRequest.py
aliyunsdkchatbot/request/v20171011/DescribeCategoryRequest.py
aliyunsdkchatbot/request/v20171011/DescribeCoreWordRequest.py
aliyunsdkchatbot/request/v20171011/DescribeDialogFlowRequest.py
aliyunsdkchatbot/request/v20171011/DescribeDialogRequest.py
aliyunsdkchatbot/request/v20171011/DescribeEntitiesRequest.py
aliyunsdkchatbot/request/v20171011/DescribeIntentRequest.py
aliyunsdkchatbot/request/v20171011/DescribeKnowledgeRequest.py
aliyunsdkchatbot/request/v20171011/DescribePerspectiveRequest.py
aliyunsdkchatbot/request/v20171011/DisableDialogFlowRequest.py
aliyunsdkchatbot/request/v20171011/DisableKnowledgeRequest.py
aliyunsdkchatbot/request/v20171011/FeedbackRequest.py
aliyunsdkchatbot/request/v20171011/MoveKnowledgeCategoryRequest.py
aliyunsdkchatbot/request/v20171011/PublishDialogFlowRequest.py
aliyunsdkchatbot/request/v20171011/PublishKnowledgeRequest.py
aliyunsdkchatbot/request/v20171011/QueryCategoriesRequest.py
